imprint/__init__.py
imprint/builder.py
imprint/components.py
imprint/engine.py
imprint/field.py
imprint/img_engine.py
imprint/model.py
imprint/page.py
imprint/pdf_engine.py
imprint/persistence.py
imprintlab-0.1.4.dist-info/licenses/LICENSE
imprintlab-0.1.4.dist-info/METADATA
imprintlab-0.1.4.dist-info/WHEEL
imprintlab-0.1.4.dist-info/top_level.txt
imprintlab-0.1.4.dist-info/RECORD
