Metadata-Version: 2.4
Name: imprintlab
Version: 0.1.4
Summary: Lib para pré-modelar certificados, crachás e templates visuais
Author-email: Daniel Fernandes <seu@email.com>
License: MIT
Classifier: Programming Language :: Python :: 3
Classifier: License :: OSI Approved :: MIT License
Classifier: Operating System :: OS Independent
Requires-Python: >=3.9
License-File: LICENSE
Requires-Dist: pydantic>=2.5.0
Requires-Dist: Pillow>=10.0.0
Provides-Extra: dev
Requires-Dist: pytest>=8.0.0; extra == "dev"
Requires-Dist: pydantic>=2.5.0; extra == "dev"
Requires-Dist: Pillow>=10.0.0; extra == "dev"
Dynamic: license-file
